splash/__init__.py
splash/_cmdline_utils.py
splash/argument_cache.py
splash/browser_tab.py
splash/casperjs_utils.py
splash/conftest.py
splash/cookies.py
splash/defaults.py
splash/errors.py
splash/har_builder.py
splash/html_element.py
splash/jsutils.py
splash/log.py
splash/lua.py
splash/lua_runner.py
splash/lua_runtime.py
splash/network_manager.py
splash/pool.py
splash/proxy.py
splash/qtrender_image.py
splash/qtrender_lua.py
splash/qtutils.py
splash/render_options.py
splash/render_scripts.py
splash/request_middleware.py
splash/resources.py
splash/response_middleware.py
splash/sentry.py
splash/server.py
splash/utils.py
splash/xvfb.py
splash/engines/chromium/__init__.py
splash/engines/chromium/browser_tab.py
splash/engines/chromium/constants.py
splash/engines/chromium/render_scripts.py
splash/engines/chromium/screenshot.py
splash/engines/chromium/webpage.py
splash/engines/webkit/__init__.py
splash/engines/webkit/browser_tab.py
splash/engines/webkit/http_client.py
splash/engines/webkit/render_scripts.py
splash/engines/webkit/screenshot.py
splash/engines/webkit/webpage.py
splash/engines/webkit/webview.py
splash/examples/block-css.lua
splash/examples/call-later.lua
splash/examples/count-divs.lua
splash/examples/disable-images.lua
splash/examples/element-screenshot.lua
splash/examples/har.lua
splash/examples/log-locked-requests.lua
splash/examples/log-requests.lua
splash/examples/multiple-pages.lua
splash/examples/preload-functions.lua
splash/examples/preload-jquery.lua
splash/examples/render-multiple.lua
splash/examples/render-png.lua
splash/examples/return-title.lua
splash/examples/run-js.lua
splash/examples/scroll.lua
splash/examples/submit-search.lua
splash/examples/wait-for-element.lua
splash/examples/with-timeout.lua
splash/har/__init__.py
splash/har/log.py
splash/har/qt.py
splash/har/schema.py
splash/har/utils.py
splash/kernel/__init__.py
splash/kernel/__main__.py
splash/kernel/completer.py
splash/kernel/errors.py
splash/kernel/inspections.py
splash-3.5.dist-info/LICENSE
splash-3.5.dist-info/METADATA
splash-3.5.dist-info/WHEEL
splash-3.5.dist-info/top_level.txt
splash-3.5.dist-info/RECORD
