Metadata-Version: 1.2
Name: splash
Version: 3.5
Summary: A javascript rendered with a HTTP API
Home-page: https://github.com/scrapinghub/splash
Author: Scrapinghub
Author-email: info@scrapinghub.com
Maintainer: Scrapinghub
Maintainer-email: info@scrapinghub.com
License: BSD
Platform: UNKNOWN
Classifier: Programming Language :: Python
Classifier: Programming Language :: Python :: 3
Classifier: Programming Language :: Python :: 3.5
Classifier: Programming Language :: Python :: 3.6
Classifier: License :: OSI Approved :: BSD License
Classifier: Operating System :: OS Independent
Classifier: Development Status :: 5 - Production/Stable
Classifier: Environment :: Console
Classifier: Environment :: No Input/Output (Daemon)
Classifier: Topic :: Internet :: WWW/HTTP
